gcpcsvhunt/gcpcsvhunt.py
gcpcsvhunt-2.2.0.dist-info/LICENSE
gcpcsvhunt-2.2.0.dist-info/METADATA
gcpcsvhunt-2.2.0.dist-info/WHEEL
gcpcsvhunt-2.2.0.dist-info/top_level.txt
gcpcsvhunt-2.2.0.dist-info/RECORD
