Metadata-Version: 2.1
Name: gcpcsvhunt
Version: 2.2.0
Summary: 
Home-page: https://github.com/soumilshah1995/GCPCsvHunt
Author: Soumil Nitin Shah
Author-email: soushah@my.bridgeport.edu
License: MIT
Platform: UNKNOWN
Classifier: License :: OSI Approved :: MIT License
Classifier: Programming Language :: Python :: 3
Classifier: Programming Language :: Python :: 3.7
Requires-Dist: google-cloud-storage
Requires-Dist: pandas
